{
  "Routes": [
    {
      "UpstreamPathTemplate": "/contracts/{everything}",
      "UpstreamHttpMethod": [ "Get" ],
      "DownstreamPathTemplate": "/contracts/{everything}",
      "DownstreamScheme": "http",
      "LoadBalancerOptions": {
        "Type": "WeightedRoundRobin"
      },
      "DownstreamHostAndPorts": [
        {
          "Host": "placeholder",
          "Port": 80
        }
      ]
    },
    {
      "UpstreamPathTemplate": "/contracts",
      "UpstreamHttpMethod": [ "Get" ],
      "DownstreamPathTemplate": "/contracts",
      "DownstreamScheme": "http",
      "LoadBalancerOptions": {
        "Type": "WeightedRoundRobin"
      },
      "DownstreamHostAndPorts": [
        {
          "Host": "placeholder",
          "Port": 80
        }
      ]
    }
  ],
  "GlobalConfiguration": {
    "BaseUrl": "http://localhost:5000"
  }
}