{
  "Routes": [
    {
      "DownstreamPathTemplate": "/api/project",
      "DownstreamScheme": "http",
      "DownstreamHostAndPorts": [
        {
          "Host": "localhost",
          "Port": 7173
        },
        {
          "Host": "localhost",
          "Port": 7174
        },
        {
          "Host": "localhost",
          "Port": 7175
        }
      ],
      "UpstreamPathTemplate": "/api/project",
      "UpstreamHttpMethod": [ "Get" ],
      "LoadBalancerOptions": {
        "Type": "WeightedRoundRobinBalancer"
      }
    }
  ],
  "GlobalConfiguration": {
    "BaseUrl": "https://localhost:7139"
  }
}
